adapted_logger-1.0.4.data/scripts/adapted_logger.py
adapted_logger-1.0.4.data/scripts/config.yml
adapted_logger-1.0.4.data/scripts/custom_adapter.py
adapted_logger-1.0.4.dist-info/DESCRIPTION.rst
adapted_logger-1.0.4.dist-info/METADATA
adapted_logger-1.0.4.dist-info/RECORD
adapted_logger-1.0.4.dist-info/WHEEL
adapted_logger-1.0.4.dist-info/entry_points.txt
adapted_logger-1.0.4.dist-info/metadata.json
adapted_logger-1.0.4.dist-info/top_level.txt
logger/__init__.py
logger/adapted_logger.py
logger/custom_adapter.py
logger/config/__init__.py
logger/config/config.yml
