Metadata-Version: 2.0
Name: adapted-logger
Version: 1.0.4
Summary: adapted_logger is a lib based on Python logging module, permetting injection of new data on logsand redirection to different target
Home-page: UNKNOWN
Author: ismailkaboubi
Author-email: ikaboubi@gmail.com
License: UNKNOWN
Keywords: logging python filters python
Platform: UNKNOWN
Classifier: Development Status :: 3 - Alpha
Classifier: Intended Audience :: Developers
Classifier: Topic :: Software Development :: Build Tools
Classifier: License :: OSI Approved :: MIT License
Classifier: Programming Language :: Python :: 2
Classifier: Programming Language :: Python :: 2.6
Classifier: Programming Language :: Python :: 2.7
